Toggle/Toggle.py
Toggle/__init__.py
Toggle-1.1.3.dist-info/LICENSE.txt
Toggle-1.1.3.dist-info/METADATA
Toggle-1.1.3.dist-info/WHEEL
Toggle-1.1.3.dist-info/top_level.txt
Toggle-1.1.3.dist-info/RECORD
