Metadata-Version: 2.1
Name: Toggle
Version: 1.1.3
Summary: Toggle is a python package for string to toggle the given string in different toggle pattern.
Home-page: https://github.com/JKL404/Toggle
Author: Laxman Khatri
Author-email: hackerlaxu@gmail.com
License: UNKNOWN
Platform: UNKNOWN
Classifier: Programming Language :: Python :: 3
Classifier: License :: OSI Approved :: MIT License
Classifier: Operating System :: OS Independent
Requires-Python: >=3.6
